headless/__init__.py
headless/core.py
headless/manager.py
headless/scraper.py
headless_driver-0.1.4.dist-info/licenses/LICENSE
headless_driver-0.1.4.dist-info/METADATA
headless_driver-0.1.4.dist-info/WHEEL
headless_driver-0.1.4.dist-info/entry_points.txt
headless_driver-0.1.4.dist-info/top_level.txt
headless_driver-0.1.4.dist-info/RECORD
