Metadata-Version: 2.4
Name: headless-driver
Version: 0.1.4
Summary: Lightweight Python library to manage Selenium Chrome WebDriver in headless mode with proxy, stealth, auto-driver installation, multi-driver management, download handling, and advanced search scraping utilities.
Author-email: nuhmanpk <nuhmanpk7@gmail.com>
License: MIT
Project-URL: Homepage, https://github.com/nuhmanpk/headless-driver
Project-URL: Documentation, https://github.com/nuhmanpk/headless-driver/wiki
Project-URL: Source, https://github.com/nuhmanpk/headless-driver
Project-URL: Issues, https://github.com/nuhmanpk/headless-driver/issues
Keywords: selenium,headless,chrome,webdriver,scraper,automation
Classifier: Development Status :: 4 - Beta
Classifier: Intended Audience :: Developers
Classifier: License :: OSI Approved :: MIT License
Classifier: Operating System :: OS Independent
Classifier: Programming Language :: Python :: 3
Classifier: Programming Language :: Python :: 3.7
Classifier: Programming Language :: Python :: 3.8
Classifier: Programming Language :: Python :: 3.9
Classifier: Programming Language :: Python :: 3.10
Classifier: Topic :: Software Development :: Libraries
Classifier: Topic :: Internet :: WWW/HTTP :: Browsers
Requires-Python: >=3.7
License-File: LICENSE
Requires-Dist: selenium==4.35.0
Requires-Dist: webdriver-manager>=4.0.0
Requires-Dist: selenium-stealth>=1.0.6
Requires-Dist: geckodriver-autoinstaller>=0.1.0
Dynamic: license-file
